{
  "cursor": "10001642_1",
  "items": [
    {
      "accrue": false,
      "bookedAccount": 1010,
      "description": "Comfort Walk Pro™ Harness - Size : XS, Color : Black",
      "discountPercentage": 0,
      "documentId": 10001522,
      "number": 1,
      "productNumber": "HAR111213",
      "projectCloseAccount": 1010,
      "quantity": 1,
      "recommendedPrice": 0,
      "totalNetAmount": 33.56,
      "unitCostPrice": 0,
      "unitNetPrice": 33.56,
      "userInterfaceNumber": 1,
      "vatAmount": 8.39,
      "vatRate": 25
    },
    {
      "accrue": false,
      "bookedAccount": 1010,
      "description": "DHL (EU) Weltpaket",
      "discountPercentage": 0,
      "documentId": 10001522,
      "number": 2,
      "productNumber": "fragtmm",
      "projectCloseAccount": 1010,
      "quantity": 1,
      "recommendedPrice": 0,
      "totalNetAmount": 6.03,
      "unitCostPrice": 0,
      "unitNetPrice": 6.03,
      "userInterfaceNumber": 2,
      "vatAmount": 1.5075,
      "vatRate": 25
    },
    {
      "accrue": false,
      "bookedAccount": 1010,
      "description": "Comfort Walk Pro™ Sele - Størrelse : XS, Farve : Black",
      "discountPercentage": 0,
      "documentId": 10001523,
      "number": 1,
      "productNumber": "HAR111213",
      "projectCloseAccount": 1010,
      "quantity": 1,
      "recommendedPrice": 0,
      "totalNetAmount": 159.5,
      "unitCostPrice": 0,
      "unitNetPrice": 159.5,
      "userInterfaceNumber": 1,
      "vatAmount": 39.875,
      "vatRate": 25
    },
    {
      "accrue": false,
      "bookedAccount": 1010,
      "description": "Comfort Walk Pro™ Sele - Størrelse : S, Farve : Ocean Blue",
      "discountPercentage": 0,
      "documentId": 10001523,
      "number": 2,
      "productNumber": "HAR111414",
      "projectCloseAccount": 1010,
      "quantity": 1,
      "recommendedPrice": 0,
      "totalNetAmount": 179.5,
      "unitCostPrice": 0,
      "unitNetPrice": 179.5,
      "userInterfaceNumber": 2,
      "vatAmount": 44.875,
      "vatRate": 25
    },
    {
      "accrue": false,
      "bookedAccount": 1010,
      "description": "Comfort Walk Pro™ Sele - Størrelse : S, Farve : Purple Passion",
      "discountPercentage": 0,
      "documentId": 10001523,
      "number": 3,
      "productNumber": "HAR111514",
      "projectCloseAccount": 1010,
      "quantity": 1,
      "recommendedPrice": 0,
      "totalNetAmount": 179.5,
      "unitCostPrice": 0,
      "unitNetPrice": 179.5,
      "userInterfaceNumber": 3,
      "vatAmount": 44.875,
      "vatRate": 25
    },
    {
      "accrue": false,
      "bookedAccount": 1010,
      "description": "Comfort Walk Pro™ Sele - Størrelse : S, Farve : Mocca",
      "discountPercentage": 0,
      "documentId": 10001523,
      "number": 4,
      "productNumber": "HAR111314",
      "projectCloseAccount": 1010,
      "quantity": 1,
      "recommendedPrice": 0,
      "totalNetAmount": 179.5,
      "unitCostPrice": 0,
      "unitNetPrice": 179.5,
      "userInterfaceNumber": 4,
      "vatAmount": 44.875,
      "vatRate": 25
    },
    {
      "accrue": false,
      "bookedAccount": 1010,
      "description": "Comfort Walk Pro™ Sele - Størrelse : M, Farve : Wild Rose",
      "discountPercentage": 0,
      "documentId": 10001523,
      "number": 5,
      "productNumber": "HAR111116",
      "projectCloseAccount": 1010,
      "quantity": 1,
      "recommendedPrice": 0,
      "totalNetAmount": 199.5,
      "unitCostPrice": 0,
      "unitNetPrice": 199.5,
      "userInterfaceNumber": 5,
      "vatAmount": 49.875,
      "vatRate": 25
    },
    {
      "accrue": false,
      "bookedAccount": 1010,
      "description": "Comfort Walk Pro™ Sele - Størrelse : M, Farve : Purple Passion",
      "discountPercentage": 0,
      "documentId": 10001523,
      "number": 6,
      "productNumber": "HAR111516",
      "projectCloseAccount": 1010,
      "quantity": 2,
      "recommendedPrice": 0,
      "totalNetAmount": 399,
      "unitCostPrice": 0,
      "unitNetPrice": 199.5,
      "userInterfaceNumber": 6,
      "vatAmount": 99.75,
      "vatRate": 25
    },
    {
      "accrue": false,
      "bookedAccount": 1010,
      "description": "Comfort Walk Pro™ Sele - Størrelse : L, Farve : Purple Passion",
      "discountPercentage": 0,
      "documentId": 10001523,
      "number": 7,
      "productNumber": "HAR111518",
      "projectCloseAccount": 1010,
      "quantity": 2,
      "recommendedPrice": 0,
      "totalNetAmount": 399,
      "unitCostPrice": 0,
      "unitNetPrice": 199.5,
      "userInterfaceNumber": 7,
      "vatAmount": 99.75,
      "vatRate": 25
    },
    {
      "accrue": false,
      "bookedAccount": 1010,
      "description": "Comfort Walk Pro™ Sele - Størrelse : L, Farve : Black",
      "discountPercentage": 0,
      "documentId": 10001523,
      "number": 8,
      "productNumber": "HAR111218",
      "projectCloseAccount": 1010,
      "quantity": 2,
      "recommendedPrice": 0,
      "totalNetAmount": 399,
      "unitCostPrice": 0,
      "unitNetPrice": 199.5,
      "userInterfaceNumber": 8,
      "vatAmount": 99.75,
      "vatRate": 25
    },
    {
      "accrue": false,
      "bookedAccount": 1010,
      "description": "Comfort Walk Pro™ Sele - Størrelse : XL, Farve : Wild Rose",
      "discountPercentage": 0,
      "documentId": 10001523,
      "number": 9,
      "productNumber": "HAR111119",
      "projectCloseAccount": 1010,
      "quantity": 1,
      "recommendedPrice": 0,
      "totalNetAmount": 199.5,
      "unitCostPrice": 0,
      "unitNetPrice": 199.5,
      "userInterfaceNumber": 9,
      "vatAmount": 49.875,
      "vatRate": 25
    },
    {
      "accrue": false,
      "bookedAccount": 1010,
      "description": "Comfort Walk Pro™ Sele - Størrelse : XL, Farve : Ocean Blue",
      "discountPercentage": 0,
      "documentId": 10001523,
      "number": 10,
      "productNumber": "HAR111419",
      "projectCloseAccount": 1010,
      "quantity": 1,
      "recommendedPrice": 0,
      "totalNetAmount": 199.5,
      "unitCostPrice": 0,
      "unitNetPrice": 199.5,
      "userInterfaceNumber": 10,
      "vatAmount": 49.875,
      "vatRate": 25
    },
    {
      "accrue": false,
      "bookedAccount": 1010,
      "description": "Urban Explorer™ Halsbånd - Størrelse : XS, Farve : Purple Passion",
      "discountPercentage": 0,
      "documentId": 10001523,
      "number": 11,
      "productNumber": "COL111513",
      "projectCloseAccount": 1010,
      "quantity": 1,
      "recommendedPrice": 0,
      "totalNetAmount": 124.5,
      "unitCostPrice": 0,
      "unitNetPrice": 124.5,
      "userInterfaceNumber": 11,
      "vatAmount": 31.125,
      "vatRate": 25
    }
  ]
}